monitoring_system2/__init__.py
monitoring_system2/agent/__init__.py
monitoring_system2/agent/agent.py
monitoring_system2/server/__init__.py
monitoring_system2/server/config.conf
monitoring_system2/server/config_loader.py
monitoring_system2/server/http_bridge.py
monitoring_system2/server/server.py
monitoring_system2/server/templates/dashboard.html
monitoring_system_report/__init__.py
monitoring_system_report/agent/__init__.py
monitoring_system_report/agent/agent.py
monitoring_system_report/server/__init__.py
monitoring_system_report/server/config_loader.py
monitoring_system_report/server/http_bridge.py
monitoring_system_report/server/server.py
monitoring_system_report2/__init__.py
monitoring_system_report2/agent/__init__.py
monitoring_system_report2/agent/agent.py
monitoring_system_report2/server/__init__.py
monitoring_system_report2/server/config_loader.py
monitoring_system_report2/server/http_bridge.py
monitoring_system_report2/server/server.py
monitoring_system_report3/__init__.py
monitoring_system_report3/agent/__init__.py
monitoring_system_report3/agent/agent.py
monitoring_system_report3/server/__init__.py
monitoring_system_report3/server/config_loader.py
monitoring_system_report3/server/http_bridge.py
monitoring_system_report3/server/server.py
monitoring_system_report4/__init__.py
monitoring_system_report4/agent/__init__.py
monitoring_system_report4/agent/agent.py
monitoring_system_report4/server/__init__.py
monitoring_system_report4/server/config_loader.py
monitoring_system_report4/server/http_bridge.py
monitoring_system_report4/server/server.py
monitoring_system_report5/__init__.py
monitoring_system_report5/agent/__init__.py
monitoring_system_report5/agent/agent.py
monitoring_system_report5/server/__init__.py
monitoring_system_report5/server/config_loader.py
monitoring_system_report5/server/http_bridge.py
monitoring_system_report5/server/server.py
server_analysis_report/__init__.py
server_analysis_report/__manifest__.py
monitoring_system_report5-0.1.2.dist-info/METADATA
monitoring_system_report5-0.1.2.dist-info/WHEEL
monitoring_system_report5-0.1.2.dist-info/entry_points.txt
monitoring_system_report5-0.1.2.dist-info/top_level.txt
monitoring_system_report5-0.1.2.dist-info/RECORD
